Metadata-Version: 1.1
Name: mixtract
Version: 3
Summary: Mixpanel data extraction / export tool
Home-page: https://github.com/markhkim/mixtract
Author: Mark Hyun-ki Kim
Author-email: email@markhkim.com
License: MIT
Download-URL: https://github.com/markhkim/mixtract/tarball/2
Keywords: mixpanel
Platform: UNKNOWN
Classifier: License :: OSI Approved :: MIT License
Classifier: Programming Language :: Python :: 3.5
Classifier: Programming Language :: Python :: 3.6
